redispatcher/__init__.py
redispatcher/base_consumer.py
redispatcher/config.py
redispatcher/exceptions.py
redispatcher/monitor.py
redispatcher/redispatcher.py
redispatcher/types.py
redispatcher-0.3.0.dist-info/LICENSE
redispatcher-0.3.0.dist-info/METADATA
redispatcher-0.3.0.dist-info/WHEEL
redispatcher-0.3.0.dist-info/entry_points.txt
redispatcher-0.3.0.dist-info/RECORD
