Metadata-Version: 2.1
Name: redispatcher
Version: 0.3.0
Summary: Dispatch and run distributed work asynchronously, brokered by Redis
Home-page: https://rafalstapinski.github.io/redispatcher
License: MIT
Keywords: redis,queue,broker,pub sub,asynchronous message,celery,dispatcher,worker
Author: Rafal Stapinski
Author-email: stapinskirafal@gmail.com
Requires-Python: >=3.8,<4.0
Classifier: License :: OSI Approved :: MIT License
Classifier: Programming Language :: Python :: 3
Classifier: Programming Language :: Python :: 3.8
Classifier: Programming Language :: Python :: 3.9
Classifier: Programming Language :: Python :: 3.10
Classifier: Programming Language :: Python :: 3.11
Classifier: Programming Language :: Python :: 3.12
Requires-Dist: aioredis (>=1.3.1,<2.0.0)
Requires-Dist: pydantic (>=2.6.1,<3.0.0)
Requires-Dist: pydantic-settings (>=2.2.1,<3.0.0)
Project-URL: Repository, https://github.com/rafalstapinski/redispatcher
